gae_app_settings/__init__.py
gae_app_settings/settings.py
gae_app_settings/tests/__init__.py
gae_app_settings/tests/settings.py
gae_app_settings/tests/test.py
gae_app_settings-1.1.1.dist-info/LICENSE
gae_app_settings-1.1.1.dist-info/METADATA
gae_app_settings-1.1.1.dist-info/WHEEL
gae_app_settings-1.1.1.dist-info/top_level.txt
gae_app_settings-1.1.1.dist-info/RECORD
