Metadata-Version: 2.1
Name: gae-app-settings
Version: 1.1.1
Summary: Provides a key/value store in Google App Engine for sensitive data.
Home-page: https://github.com/seawolf42/gae-app-settings
Author: jeffrey k eliasen
Author-email: jeff+gae-app-settings@jke.net
License: MIT License
Platform: UNKNOWN
Classifier: Environment :: Web Environment
Classifier: Intended Audience :: Developers
Classifier: License :: OSI Approved :: MIT License
Classifier: Operating System :: OS Independent
Classifier: Programming Language :: Python
Classifier: Programming Language :: Python :: 2.7
Classifier: Topic :: Internet :: WWW/HTTP :: Site Management
